pcrypto/__init__.py
pcrypto/cryptoSystem/__init__.py
pcrypto/cryptoSystem/affine.py
pcrypto/cryptoSystem/ecc.py
pcrypto/cryptoSystem/elgamal.py
pcrypto/cryptoSystem/rsa.py
pcrypto/cryptoSystem/shiftcipher.py
pcrypto/cryptoSystem/vigenere.py
pcrypto/ellipticCurve/Koblitz.py
pcrypto/ellipticCurve/__init__.py
pcrypto/ellipticCurve/curve.py
pcrypto/ellipticCurve/domain.py
pcrypto/ellipticCurve/point.py
pcrypto/hash/__init__.py
pcrypto/hash/md4.py
pcrypto/hash/sha256.py
pcrypto/prime/__init__.py
pcrypto/prime/aks.py
pcrypto/prime/generator.py
pcrypto/prime/millerRabin.py
pcrypto/prime/primality.py
pcrypto/prime/smallPrimes.py
pcrypto/signatureScheme/__init__.py
pcrypto/signatureScheme/ecdsa.py
pcrypto/signatureScheme/elgamal.py
pcrypto/signatureScheme/rsa.py
pcrypto/utils.py
pcrypto-0.1.1.dist-info/METADATA
pcrypto-0.1.1.dist-info/WHEEL
pcrypto-0.1.1.dist-info/RECORD
